FreeNove_Rover/Battery.py
FreeNove_Rover/Buzzer.py
FreeNove_Rover/LED_Matrix.py
FreeNove_Rover/MotorControl.py
FreeNove_Rover/Servo.py
FreeNove_Rover/__init__.py
FreeNove_4WD_Rover_Pico-0.1.1.dist-info/METADATA
FreeNove_4WD_Rover_Pico-0.1.1.dist-info/WHEEL
FreeNove_4WD_Rover_Pico-0.1.1.dist-info/top_level.txt
FreeNove_4WD_Rover_Pico-0.1.1.dist-info/RECORD
