Metadata-Version: 2.1
Name: FreeNove_4WD-Rover_Pico
Version: 0.1.1
Summary: A package for controlling the FreeNove 4WD Rover for pi pico using micropython. This package has been adapted from the arduino-pico version.
Author: AstroScott
Classifier: Programming Language :: Python :: 3
Classifier: License :: OSI Approved :: MIT License
Classifier: Operating System :: OS Independent
Requires-Python: >=3.6
